codehelp/__init__.py
codehelp/getgitcontents.py
codehelp/gisthandler.py
codehelp-0.0.1.dist-info/LICENSE.md
codehelp-0.0.1.dist-info/METADATA
codehelp-0.0.1.dist-info/WHEEL
codehelp-0.0.1.dist-info/top_level.txt
codehelp-0.0.1.dist-info/RECORD
