Metadata-Version: 2.1
Name: codehelp
Version: 0.0.1
Summary: Module that help to shorten time and aid in writing code
Home-page: https://github.com/spidezad/codehelp
Author: Tan Kok Hua
Author-email: kokhua81@gmail.com
License: BSD
Download-URL: https://github.com/spidezad/codehelp/tarball/0.0.1
Platform: UNKNOWN
Classifier: Development Status :: 3 - Alpha
Classifier: Intended Audience :: Developers
Classifier: Programming Language :: Python :: 3
Requires-Dist: sphinx
Requires-Dist: sphinx-rtd-theme
Requires-Dist: nose
Requires-Dist: coverage
Requires-Dist: pypi-publisher
